helper/__init__.py
helper/sample_args.py
parser/__init__.py
parser/pylogex.py
parser/regex.py
plugins/__init__.py
plugins/csvHelper.py
plugins/jsonHelper.py
tests/__init__.py
tests/test_csvConverter.py
tests/test_jsonConverter.py
tests/test_regex.py
utility/__init__.py
utility/check_format.py
utility/utility_component.py
Pylogex-0.0.1.dist-info/LICENSE.txt
Pylogex-0.0.1.dist-info/METADATA
Pylogex-0.0.1.dist-info/WHEEL
Pylogex-0.0.1.dist-info/top_level.txt
Pylogex-0.0.1.dist-info/RECORD
