Metadata-Version: 2.1
Name: Pylogex
Version: 0.0.1
Summary: A simple python log extractor
Home-page: https://git.corp.adobe.com/rkayal/pylogex
Author: Sanskriti Ritika Saumya Surabhi
Author-email: surabhis@adobe.com
License: : OSI Approved :: MIT License
License-File: LICENSE.txt
